<Document>
  # Инженерное дело
  [color=#f39f27]Инженерия[/color] — это и [textlink="строительство" link="Construction"], и [textlink="ремонт" link="ExpandingRepairingStation"], и обслуживание машины смерти, которая заодно производит [textlink="электроэнергию" link="Power"], и забота о том, чтобы на станции был [textlink="воздух" link="Atmospherics"].

  ## Персонал
  В [color=#f39f27]инженерии[/color] работают технические ассистенты, инженеры станции и техники атмосферы.
  Руководит отделом главный инженер.

  <Box>
    <GuideEntityEmbed Entity="ToyFigurineEngineer" Caption="Инженер"/>
    <GuideEntityEmbed Entity="ToyFigurineAtmosTech" Caption="Атмосник"/>
    <GuideEntityEmbed Entity="ToyFigurineChiefEngineer" Caption="ГИ"/>
  </Box>

  ## Инструменты
  <Box>
    <GuideEntityEmbed Entity="Wrench"/>
    <GuideEntityEmbed Entity="Crowbar"/>
    <GuideEntityEmbed Entity="Screwdriver"/>
    <GuideEntityEmbed Entity="Wirecutter"/>
  </Box>
  <Box>
    <GuideEntityEmbed Entity="Welder"/>
    <GuideEntityEmbed Entity="Multitool"/>
    <GuideEntityEmbed Entity="NetworkConfigurator"/>
  </Box>
  Базовый набор — несколько ключевых инструментов. Инженер обычно носит пояс с комплектом; иначе их можно найти в техтоннелях и хранилищах инструментов (ящики, автоматы).

  Большинство задач подскажут следующий шаг при осмотре объекта; например, при [textlink="постройке" link="Construction"] стены осмотрите её — увидите, что делать дальше.
</Document>
